dftxt/__init__.py
dftxt/_io/__init__.py
dftxt/_io/_cast.py
dftxt/_io/_markdown.py
dftxt/_io/_modifiers.py
dftxt/_io/_read.py
dftxt/_io/_write.py
dftxt/cli/__init__.py
dftxt/tests/__init__.py
dftxt/tests/_examples/__init__.py
dftxt/tests/_examples/multiple_frames_filtering/frames.dftxt
dftxt/tests/_examples/multiple_frames_filtering/test_multiple_frames_filtering.py
dftxt/tests/_examples/multiple_frames_named/frames.dftxt
dftxt/tests/_examples/multiple_frames_named/test_multiple_frames_named.py
dftxt/tests/_examples/multiple_frames_unnamed/frames.dftxt
dftxt/tests/_examples/multiple_frames_unnamed/test_multiple_frames_unnamed.py
dftxt/tests/_io/__init__.py
dftxt/tests/_io/_markdown/__init__.py
dftxt/tests/_io/_markdown/scenarios/multiple_frames/extracted.dftxt
dftxt/tests/_io/_markdown/scenarios/multiple_frames/source.md
dftxt/tests/_io/_markdown/scenarios/single_frame/extracted.dftxt
dftxt/tests/_io/_markdown/scenarios/single_frame/source.md
dftxt/tests/_io/_markdown/test_markdown.py
dftxt/tests/_io/_modifiers/scenarios/basic.json
dftxt/tests/_io/_modifiers/scenarios/empty.json
dftxt/tests/_io/_modifiers/test_modifier_scenarios.py
dftxt/tests/_io/_read/__init__.py
dftxt/tests/_io/_read/test_find_columns.py
dftxt/tests/_io/scenarios/anagrams/expected.py
dftxt/tests/_io/scenarios/anagrams/scenario.json
dftxt/tests/_io/scenarios/anagrams/source.dftxt
dftxt/tests/_io/scenarios/anscombe/expected.py
dftxt/tests/_io/scenarios/anscombe/scenario.json
dftxt/tests/_io/scenarios/anscombe/source.dftxt
dftxt/tests/_io/scenarios/attention/expected.py
dftxt/tests/_io/scenarios/attention/scenario.json
dftxt/tests/_io/scenarios/attention/source.dftxt
dftxt/tests/_io/scenarios/brain_networks/expected.py
dftxt/tests/_io/scenarios/brain_networks/scenario.json
dftxt/tests/_io/scenarios/brain_networks/source.dftxt
dftxt/tests/_io/scenarios/car_crashes/expected.py
dftxt/tests/_io/scenarios/car_crashes/scenario.json
dftxt/tests/_io/scenarios/car_crashes/source.dftxt
dftxt-1.0.3.dist-info/LICENSE
dftxt-1.0.3.dist-info/METADATA
dftxt-1.0.3.dist-info/WHEEL
dftxt-1.0.3.dist-info/entry_points.txt
dftxt-1.0.3.dist-info/RECORD
