Metadata-Version: 2.1
Name: dftxt
Version: 1.0.3
Summary: Human-friendly, VCS-friendly file format for Python Pandas and Polars DataFrames.
Home-page: https://github.com/rocketboosters/dftxt
License: Apache Version 2.0
Author: Scott Ernst
Author-email: swernst@gmail.com
Requires-Python: >=3.9,<4.0
Classifier: Development Status :: 5 - Production/Stable
Classifier: License :: Other/Proprietary License
Classifier: Programming Language :: Python :: 3
Classifier: Programming Language :: Python :: 3.9
Classifier: Programming Language :: Python :: 3.10
Classifier: Programming Language :: Python :: 3.11
Classifier: Programming Language :: Python :: 3.12
Classifier: Programming Language :: Python :: 3.8
Classifier: Topic :: File Formats
Classifier: Topic :: Software Development :: Testing
Classifier: Typing :: Typed
Provides-Extra: all
Provides-Extra: pandas
Provides-Extra: polars
Requires-Dist: pandas (>=2.0.0) ; extra == "pandas" or extra == "all"
Requires-Dist: polars (>=0.20.5,<0.21.0) ; extra == "polars" or extra == "all"
Requires-Dist: pyarrow (>=14.0.2,<15.0.0) ; extra == "pandas" or extra == "all"
Requires-Dist: pytz (>=2020.1)
Project-URL: Documentation, https://github.com/rocketboosters/dftxt
Project-URL: Repository, https://github.com/rocketboosters/dftxt
